pydensity/__init__.py
pydensity/backends/__init__.py
pydensity/backends/cffi/__init__.py
pydensity/backends/cffi/_density.pypy39-pp73-win_amd64.pyd
pydensity/backends/cffi/build.py
pydensity/backends/cython/__init__.py
pydensity/backends/cython/_density.c
pydensity/backends/cython/_density.pypy39-pp73-win_amd64.pyd
pydensity-0.1.1.dist-info/METADATA
pydensity-0.1.1.dist-info/WHEEL
pydensity-0.1.1.dist-info/top_level.txt
pydensity-0.1.1.dist-info/RECORD
