Metadata-Version: 2.1
Name: pydensity
Version: 0.1.1
Summary: compress and decompress
Home-page: https://github.com/synodriver/pydensity
Author: synodriver
Author-email: diguohuangjiajinweijun@gmail.com
License: BSD
Keywords: compress,decompress,density
Classifier: Development Status :: 4 - Beta
Classifier: Operating System :: OS Independent
Classifier: License :: OSI Approved :: BSD License
Classifier: Topic :: Multimedia :: Sound/Audio
Classifier: Programming Language :: C
Classifier: Programming Language :: Cython
Classifier: Programming Language :: Python
Classifier: Programming Language :: Python :: 3.6
Classifier: Programming Language :: Python :: 3.7
Classifier: Programming Language :: Python :: 3.8
Classifier: Programming Language :: Python :: 3.9
Classifier: Programming Language :: Python :: 3.10
Classifier: Programming Language :: Python :: 3.11
Classifier: Programming Language :: Python :: Implementation :: CPython
Classifier: Programming Language :: Python :: Implementation :: PyPy
Requires-Python: >=3.6
Requires-Dist: cffi (>=1.0.0)
